pylibrenms/__init__.py
pylibrenms/client.py
pylibrenms-0.4.15.dist-info/METADATA
pylibrenms-0.4.15.dist-info/WHEEL
pylibrenms-0.4.15.dist-info/licenses/LICENSE
pylibrenms-0.4.15.dist-info/RECORD
